 

[

    {

        "pytanie":"w którym roku pojawil sie Python",
        "a":1986,
        "b":1991,
        "c":1995,
        "d":2000,
        "prawidlowa_odpowiedz" :"b"



    },


    {

        "pytanie":"która planeta od słonca jest ziemia",
        "a":1,
        "b":2,
        "c":3,
        "d":4,
        "prawidlowa_odpowiedz" :"c"



    },

 
    {

        "pytanie":"który aktor wcielił się jako pierwszy w rolę Jamesa Bonda",
        "a":"Sean Connery",
        "b":"Roger moore",
        "c":"Timoty dalton",
        "d":"Pierce Brosnan",
        "prawidlowa_odpowiedz" :"a"



    }





]